{
    "address1": "131, Maker Tower-F Premises",
    "address2": "13th Floor Cuffe Parade",
    "city": "Mumbai",
    "zip": "400005",
    "country": "India",
    "phone": "91 22 2217 8600",
    "fax": "91 22 2217 8777",
    "website": "https://www.lichousing.com",
    "industry": "Mortgage Finance",
    "industryKey": "mortgage-finance",
    "industryDisp": "Mortgage Finance",
    "sector": "Financial Services",
    "sectorKey": "financial-services",
    "sectorDisp": "Financial Services",
    "longBusinessSummary": "LIC Housing Finance Limited, a housing finance company, provides loans for the purchase, construction, repair, and renovation of houses/buildings in India. The company offers public, green, and corporate deposits; home loans to residents and non-residents Indians, as well as to pensioners; plot loans, home improvement and renovation, construction, and home extension loans; refinance; construction finance and term loans for builders and developers; and loans for staff quarters and other lines of credit for corporates. It also provides loans against properties for companies and individuals; loans against rental securitization; and loans to professionals. In addition, the company develops, establishes, and operates assisted living community centers for elderly citizens; manages, advises, and administers private equity funds, including venture capital and alternate investment funds; offers asset management and trusteeship services; and markets housing loan, life and general insurance products, mutual funds, fixed deposits, and credit cards. LIC Housing Finance Limited was incorporated in 1989 and is based in Mumbai, India.",
    "fullTimeEmployees": 2352,
    "companyOfficers": [
        {
            "maxAge": 1,
            "name": "Mr. Tribhuwan  Adhikari",
            "title": "CEO, MD & Additional Director",
            "fiscalYear": 2025,
            "totalPay": 10602709,
            "exercisedValue": 0,
            "unexercisedValue": 0
        },
        {
            "maxAge": 1,
            "name": "Mr. Sudipto  Sil",
            "title": "Marketing Head of Western Region at Mumbai",
            "fiscalYear": 2025,
            "exercisedValue": 0,
            "unexercisedValue": 0
        },
        {
            "maxAge": 1,
            "name": "Ms. Varsha  Hardasani",
            "title": "Company Secretary & Compliance Officer",
            "fiscalYear": 2025,
            "exercisedValue": 0,
            "unexercisedValue": 0
        },
        {
            "maxAge": 1,
            "name": "Mr. Lokesh  Mundhra",
            "title": "Chief Financial Officer",
            "fiscalYear": 2025,
            "exercisedValue": 0,
            "unexercisedValue": 0
        },
        {
            "maxAge": 1,
            "name": "Mr. Sanjay  Dayal",
            "age": 56,
            "title": "Chief Operating Officer",
            "yearBorn": 1969,
            "fiscalYear": 2025,
            "exercisedValue": 0,
            "unexercisedValue": 0
        },
        {
            "maxAge": 1,
            "name": "Mr. H J Panchariya",
            "title": "General Manager of Accounts & Treasury",
            "fiscalYear": 2025,
            "exercisedValue": 0,
            "unexercisedValue": 0
        },
        {
            "maxAge": 1,
            "name": "Mr. Hitesh B. Talreja",
            "title": "Chief Technology Officer",
            "fiscalYear": 2025,
            "exercisedValue": 0,
            "unexercisedValue": 0
        },
        {
            "maxAge": 1,
            "name": "Mr. R.  Murali",
            "title": "Chief Compliance Officer",
            "fiscalYear": 2025,
            "exercisedValue": 0,
            "unexercisedValue": 0
        },
        {
            "maxAge": 1,
            "name": "Mr. Debakanta  Padhi",
            "title": "General Manager of HR, Staff Discipline & Legal",
            "fiscalYear": 2025,
            "exercisedValue": 0,
            "unexercisedValue": 0
        },
        {
            "maxAge": 1,
            "name": "Mr. J.  Sangameswar",
            "title": "Chief Risk Officer",
            "fiscalYear": 2025,
            "exercisedValue": 0,
            "unexercisedValue": 0
        }
    ],
    "auditRisk": 10,
    "boardRisk": 7,
    "compensationRisk": 4,
    "shareHolderRightsRisk": 1,
    "overallRisk": 6,
    "governanceEpochDate": 1775001600,
    "compensationAsOfEpochDate": 1767139200,
    "executiveTeam": [],
    "maxAge": 86400,
    "priceHint": 2,
    "previousClose": 565.15,
    "open": 567.4,
    "dayLow": 556.25,
    "dayHigh": 568.55,
    "regularMarketPreviousClose": 565.15,
    "regularMarketOpen": 567.4,
    "regularMarketDayLow": 556.25,
    "regularMarketDayHigh": 568.55,
    "dividendRate": 10.0,
    "dividendYield": 1.77,
    "exDividendDate": 1755820800,
    "payoutRatio": 0.1003,
    "fiveYearAvgDividendYield": 1.86,
    "beta": 0.241,
    "trailingPE": 5.6078844,
    "forwardPE": 5.4207606,
    "volume": 1433586,
    "regularMarketVolume": 1433586,
    "averageVolume": 1829714,
    "averageVolume10days": 1737241,
    "averageDailyVolume10Day": 1737241,
    "bid": 0.0,
    "ask": 0.0,
    "bidSize": 0,
    "askSize": 0,
    "marketCap": 307512705024,
    "nonDilutedMarketCap": 310868104450,
    "fiftyTwoWeekLow": 458.9,
    "fiftyTwoWeekHigh": 646.5,
    "allTimeHigh": 826.75,
    "allTimeLow": 11.36,
    "priceToSalesTrailing12Months": 3.652417,
    "fiftyDayAverage": 515.553,
    "twoHundredDayAverage": 547.842,
    "trailingAnnualDividendRate": 10.0,
    "trailingAnnualDividendYield": 0.017694417,
    "currency": "INR",
    "tradeable": false,
    "enterpriseValue": 2916717690880,
    "profitMargins": 0.65141,
    "floatShares": 299743847,
    "sharesOutstanding": 550063000,
    "heldPercentInsiders": 0.02349,
    "heldPercentInstitutions": 0.75031,
    "impliedSharesOutstanding": 550063000,
    "bookValue": 700.243,
    "priceToBook": 0.7983657,
    "lastFiscalYearEnd": 1743379200,
    "nextFiscalYearEnd": 1774915200,
    "mostRecentQuarter": 1767139200,
    "earningsQuarterlyGrowth": -0.026,
    "netIncomeToCommon": 54845300736,
    "trailingEps": 99.69,
    "forwardEps": 103.13128,
    "lastSplitFactor": "5:1",
    "lastSplitDate": 1293667200,
    "enterpriseToRevenue": 34.643,
    "52WeekChange": -0.079110324,
    "SandP52WeekChange": 0.3140242,
    "lastDividendValue": 10.0,
    "lastDividendDate": 1755820800,
    "quoteType": "EQUITY",
    "currentPrice": 559.05,
    "targetHighPrice": 940.0,
    "targetLowPrice": 410.0,
    "targetMeanPrice": 593.25,
    "targetMedianPrice": 595.0,
    "recommendationMean": 2.56,
    "recommendationKey": "hold",
    "numberOfAnalystOpinions": 24,
    "totalCash": 10607699968,
    "totalCashPerShare": 19.288,
    "totalDebt": 2616472895488,
    "totalRevenue": 84194304000,
    "debtToEquity": 679.251,
    "revenuePerShare": 153.065,
    "grossProfits": 82347401216,
    "earningsGrowth": -0.026,
    "revenueGrowth": -0.02,
    "grossMargins": 0.97806,
    "ebitdaMargins": 0.0,
    "operatingMargins": 0.83098,
    "financialCurrency": "INR",
    "symbol": "LICHSGFIN.NS",
    "language": "en-US",
    "region": "US",
    "typeDisp": "Equity",
    "quoteSourceName": "Delayed Quote",
    "triggerable": true,
    "customPriceAlertConfidence": "HIGH",
    "marketState": "POSTPOST",
    "exchange": "NSI",
    "messageBoardId": "finmb_882362",
    "exchangeTimezoneName": "Asia/Kolkata",
    "exchangeTimezoneShortName": "IST",
    "gmtOffSetMilliseconds": 19800000,
    "esgPopulated": false,
    "shortName": "LIC HOUSING FINANCE LTD",
    "longName": "LIC Housing Finance Limited",
    "hasPrePostMarketData": false,
    "firstTradeDateMilliseconds": 1025495100000,
    "regularMarketChange": -6.1000366,
    "regularMarketDayRange": "556.25 - 568.55",
    "fullExchangeName": "NSE",
    "averageDailyVolume3Month": 1829714,
    "fiftyTwoWeekLowChange": 100.149994,
    "fiftyTwoWeekLowChangePercent": 0.21823926,
    "fiftyTwoWeekRange": "458.9 - 646.5",
    "fiftyTwoWeekHighChange": -87.45001,
    "fiftyTwoWeekHighChangePercent": -0.13526684,
    "fiftyTwoWeekChangePercent": -7.9110327,
    "earningsTimestamp": 1769767200,
    "earningsTimestampStart": 1778752800,
    "earningsTimestampEnd": 1778752800,
    "earningsCallTimestampStart": 1770012000,
    "earningsCallTimestampEnd": 1770012000,
    "isEarningsDateEstimate": true,
    "epsTrailingTwelveMonths": 99.69,
    "epsForward": 103.13128,
    "epsCurrentYear": 99.1379,
    "priceEpsCurrentYear": 5.6391144,
    "fiftyDayAverageChange": 43.49701,
    "fiftyDayAverageChangePercent": 0.08436962,
    "twoHundredDayAverageChange": 11.208008,
    "twoHundredDayAverageChangePercent": 0.02045847,
    "sourceInterval": 15,
    "exchangeDataDelayedBy": 15,
    "averageAnalystRating": "2.6 - Hold",
    "cryptoTradeable": false,
    "corporateActions": [],
    "regularMarketTime": 1776851998,
    "market": "in_market",
    "regularMarketChangePercent": -1.0793658,
    "regularMarketPrice": 559.05,
    "trailingPegRatio": null
}